{
  "schemaVersion": 1,
  "id": "blossom",
  "version": "${version}",

  "name": "Blossom",
  "description": "Fruit blossoms from trees!",
  "authors": [
    "yurisuika"
  ],
  "contributors": [
  ],
  "contact": {
    "homepage": "https://yurisuika.dev",
    "sources": "https://github.com/yurisuika/Blossom",
    "issues": "https://github.com/yurisuika/Blossom/issues"
  },

  "license": "GNU Lesser General Public License v3.0",
  "icon": "assets/blossom/icon.png",

  "environment": "*",
  "entrypoints": {
    "main": [
      "dev.yurisuika.blossom.Blossom"
    ],
    "client": [
      "dev.yurisuika.blossom.Blossom"
    ]
  },
  "mixins": [
    "blossom.mixins.json"
  ],

  "accessWidener" : "blossom.accesswidener",

  "depends": {
    "fabricloader": ">=0.14.21",
    "minecraft": "1.20.x",
    "java": ">=17"
  }
}